Workbook

Sheet order_items (2)
A1: order_id | B1: item_id | C1: product_id | D1: quantity | E1: list_price | F1: discount | G1: total_price | H1: product name | I1: category_id | J1: category_name
A2: 1364 | B2: 2 | C2: 155 | D2: 2 | E2: 11999.99 | F2: 0.1 | G2: =(E2*B2)-F2 -> 23999.88 | H2: =VLOOKUP($C2,products!$A$1:$F$322,2,FALSE) -> Trek Domane SLR 9 Disc - 2018 | I2: =_xlfn.XLOOKUP(C2, products!A:A, products!D:D) -> 7 | J2: =_xlfn.XLOOKUP($I2,categories!$A$1:$A$8,categories!$B$1:$B$8) -> Road Bikes
A3: 1541 | B3: 1 | C3: 155 | D3: 2 | E3: 11999.99 | F3: 0.1 | G3: =(E3*B3)-F3 -> 11999.89 | H3: =VLOOKUP($C3,products!$A$1:$F$322,2,FALSE) -> Trek Domane SLR 9 Disc - 2018 | I3: =_xlfn.XLOOKUP(C3, products!A:A, products!D:D) -> 7 | J3: =_xlfn.XLOOKUP($I3,categories!$A$1:$A$8,categories!$B$1:$B$8) -> Road Bikes
A4: 1570 | B4: 1 | C4: 155 | D4: 1 | E4: 11999.99 | F4: 0.07 | G4: =(E4*B4)-F4 -> 11999.92 | H4: =VLOOKUP($C4,products!$A$1:$F$322,2,FALSE) -> Trek Domane SLR 9 Disc - 2018 | I4: =_xlfn.XLOOKUP(C4, products!A:A, products!D:D) -> 7 | J4: =_xlfn.XLOOKUP($I4,categories!$A$1:$A$8,categories!$B$1:$B$8) -> Road Bikes
A5: 1355 | B5: 3 | C5: 149 | D5: 1 | E5: 7499.99 | F5: 0.2 | G5: =(E5*B5)-F5 -> 22499.77 | H5: =VLOOKUP($C5,products!$A$1:$F$322,2,FALSE) -> Trek Domane SLR 8 Disc - 2018 | I5: =_xlfn.XLOOKUP(C5, products!A:A, products!D:D) -> 7 | J5: =_xlfn.XLOOKUP($I5,categories!$A$1:$A$8,categories!$B$1:$B$8) -> Road Bikes
A6: 1439 | B6: 4 | C6: 149 | D6: 1 | E6: 7499.99 | F6: 0.05 | G6: =(E6*B6)-F6 -> 29999.91 | H6: =VLOOKUP($C6,products!$A$1:$F$322,2,FALSE) -> Trek Domane SLR 8 Disc - 2018 | I6: =_xlfn.XLOOKUP(C6, products!A:A, products!D:D) -> 7 | J6: =_xlfn.XLOOKUP($I6,categories!$A$1:$A$8,categories!$B$1:$B$8) -> Road Bikes
A7: 1506 | B7: 3 | C7: 149 | D7: 2 | E7: 7499.99 | F7: 0.05 | G7: =(E7*B7)-F7 -> 22499.92 | H7: =VLOOKUP($C7,products!$A$1:$F$322,2,FALSE) -> Trek Domane SLR 8 Disc - 2018 | I7: =_xlfn.XLOOKUP(C7, products!A:A, products!D:D) -> 7 | J7: =_xlfn.XLOOKUP($I7,categories!$A$1:$A$8,categories!$B$1:$B$8) -> Road Bikes
A8: 672 | B8: 1 | C8: 51 | D8: 2 | E8: 6499.99 | F8: 0.07 | G8: =(E8*B8)-F8 -> 6499.92 | H8: =VLOOKUP($C8,products!$A$1:$F$322,2,FALSE) -> Trek Silque SLR 8 Women's - 2017 | I8: =_xlfn.XLOOKUP(C8, products!A:A, products!D:D) -> 7 | J8: =_xlfn.XLOOKUP($I8,categories!$A$1:$A$8,categories!$B$1:$B$8) -> Road Bikes
A9: 787 | B9: 1 | C9: 51 | D9: 2 | E9: 6499.99 | F9: 0.07 | G9: =(E9*B9)-F9 -> 6499.92 | H9: =VLOOKUP($C9,products!$A$1:$F$322,2,FALSE) -> Trek Silque SLR 8 Women's - 2017 | I9: =_xlfn.XLOOKUP(C9, products!A:A, products!D:D) -> 7 | J9: =_xlfn.XLOOKUP($I9,categories!$A$1:$A$8,categories!$B$1:$B$8) -> Road Bikes
A10: 837 | B10: 1 | C10: 51 | D10: 1 | E10: 6499.99 | F10: 0.05 | G10: =(E10*B10)-F10 -> 6499.94 | H10: =VLOOKUP($C10,products!$A$1:$F$322,2,FALSE) -> Trek Silque SLR 8 Women's - 2017 | I10: =_xlfn.XLOOKUP(C10, products!A:A, products!D:D) -> 7 | J10: =_xlfn.XLOOKUP($I10,categories!$A$1:$A$8,categories!$B$1:$B$8) -> Road Bikes
A11: 904 | B11: 2 | C11: 51 | D11: 2 | E11: 6499.99 | F11: 0.07 | G11: =(E11*B11)-F11 -> 12999.91 | H11: =VLOOKUP($C11,products!$A$1:$F$322,2,FALSE) -> Trek Silque SLR 8 Women's - 2017 | I11: =_xlfn.XLOOKUP(C11, products!A:A, products!D:D) -> 7 | J11: =_xlfn.XLOOKUP($I11,categories!$A$1:$A$8,categories!$B$1:$B$8) -> Road Bikes
A12: 930 | B12: 5 | C12: 51 | D12: 2 | E12: 6499.99 | F12: 0.1 | G12: =(E12*B12)-F12 -> 32499.85 | H12: =VLOOKUP($C12,products!$A$1:$F$322,2,FALSE) -> Trek Silque SLR 8 Women's - 2017 | I12: =_xlfn.XLOOKUP(C12, products!A:A, products!D:D) -> 7 | J12: =_xlfn.XLOOKUP($I12,categories!$A$1:$A$8,categories!$B$1:$B$8) -> Road Bikes
A13: 937 | B13: 2 | C13: 51 | D13: 2 | E13: 6499.99 | F13: 0.07 | G13: =(E13*B13)-F13 -> 12999.91 | H13: =VLOOKUP($C13,products!$A$1:$F$322,2,FALSE) -> Trek Silque SLR 8 Women's - 2017 | I13: =_xlfn.XLOOKUP(C13, products!A:A, products!D:D) -> 7 | J13: =_xlfn.XLOOKUP($I13,categories!$A$1:$A$8,categories!$B$1:$B$8) -> Road Bikes
... A4723: 1573 | B4723: 5 | C4723: 263 | D4723: 2 | E4723: 89.99 | F4723: 0.1 | G4723: =(E4723*B4723)-F4723 -> 449.85 | H4723: =VLOOKUP($C4723,products!$A$1:$F$322,2,FALSE) -> Strider Classic 12 Balance Bike - 2018 | I4723: =_xlfn.XLOOKUP(C4723, products!A:A, products!D:D) -> 1 | J4723: =_xlfn.XLOOKUP($I4723,categories!$A$1:$A$8,categories!$B$1:$B$8) -> Children Bicycles

Sheet stores
A1: store_id | B1: store_name | C1: phone | D1: email | E1: street | F1: city | G1: state | H1: zip_code
A2: 1 | B2: Santa Cruz Bikes | C2: (831) 476-4321 | D2: santacruz@bikes.shop | E2: 3700 Portola Drive | F2: Santa Cruz | G2: CA | H2: 95060
A3: 2 | B3: Baldwin Bikes | C3: (516) 379-8888 | D3: baldwin@bikes.shop | E3: 4200 Chestnut Lane | F3: Baldwin | G3: NY | H3: 11432
A4: 3 | B4: Rowlett Bikes | C4: (972) 530-5555 | D4: rowlett@bikes.shop | E4: 8000 Fairway Avenue | F4: Rowlett | G4: TX | H4: 75088

Sheet stocks
A1: store_id | B1: product_id | C1: quantity
A2: 1 | B2: 1 | C2: 27
A3: 1 | B3: 2 | C3: 5
A4: 1 | B4: 3 | C4: 6
A5: 1 | B5: 4 | C5: 23
A6: 1 | B6: 5 | C6: 22
A7: 1 | B7: 6 | C7: 0
A8: 1 | B8: 7 | C8: 8
A9: 1 | B9: 8 | C9: 0
A10: 1 | B10: 9 | C10: 11
A11: 1 | B11: 10 | C11: 15
A12: 1 | B12: 11 | C12: 8
A13: 1 | B13: 12 | C13: 16
... A940: 3 | B940: 313 | C940: 0

Sheet order_items (3)
A1: order_id | B1: item_id | C1: product_id | D1: quantity | E1: list_price | F1: discount | G1: total_price | H1: product name | I1: category_id | J1: category_name
A2: 1364 | B2: 2 | C2: 155 | D2: 2 | E2: 11999.99 | F2: 0.1 | G2: =(E2*B2)-F2 -> 23999.88 | H2: =VLOOKUP($C2,products!$A$1:$F$322,2,FALSE) -> Trek Domane SLR 9 Disc - 2018 | I2: =_xlfn.XLOOKUP(C2, products!A:A, products!D:D) -> 7 | J2: =_xlfn.XLOOKUP($I2,categories!$A$1:$A$8,categories!$B$1:$B$8) -> Road Bikes
A3: 1541 | B3: 1 | C3: 155 | D3: 2 | E3: 11999.99 | F3: 0.1 | G3: =(E3*B3)-F3 -> 11999.89 | H3: =VLOOKUP($C3,products!$A$1:$F$322,2,FALSE) -> Trek Domane SLR 9 Disc - 2018 | I3: =_xlfn.XLOOKUP(C3, products!A:A, products!D:D) -> 7 | J3: =_xlfn.XLOOKUP($I3,categories!$A$1:$A$8,categories!$B$1:$B$8) -> Road Bikes
A4: 1570 | B4: 1 | C4: 155 | D4: 1 | E4: 11999.99 | F4: 0.07 | G4: =(E4*B4)-F4 -> 11999.92 | H4: =VLOOKUP($C4,products!$A$1:$F$322,2,FALSE) -> Trek Domane SLR 9 Disc - 2018 | I4: =_xlfn.XLOOKUP(C4, products!A:A, products!D:D) -> 7 | J4: =_xlfn.XLOOKUP($I4,categories!$A$1:$A$8,categories!$B$1:$B$8) -> Road Bikes
A5: 1355 | B5: 3 | C5: 149 | D5: 1 | E5: 7499.99 | F5: 0.2 | G5: =(E5*B5)-F5 -> 22499.77 | H5: =VLOOKUP($C5,products!$A$1:$F$322,2,FALSE) -> Trek Domane SLR 8 Disc - 2018 | I5: =_xlfn.XLOOKUP(C5, products!A:A, products!D:D) -> 7 | J5: =_xlfn.XLOOKUP($I5,categories!$A$1:$A$8,categories!$B$1:$B$8) -> Road Bikes
A6: 1439 | B6: 4 | C6: 149 | D6: 1 | E6: 7499.99 | F6: 0.05 | G6: =(E6*B6)-F6 -> 29999.91 | H6: =VLOOKUP($C6,products!$A$1:$F$322,2,FALSE) -> Trek Domane SLR 8 Disc - 2018 | I6: =_xlfn.XLOOKUP(C6, products!A:A, products!D:D) -> 7 | J6: =_xlfn.XLOOKUP($I6,categories!$A$1:$A$8,categories!$B$1:$B$8) -> Road Bikes
A7: 1506 | B7: 3 | C7: 149 | D7: 2 | E7: 7499.99 | F7: 0.05 | G7: =(E7*B7)-F7 -> 22499.92 | H7: =VLOOKUP($C7,products!$A$1:$F$322,2,FALSE) -> Trek Domane SLR 8 Disc - 2018 | I7: =_xlfn.XLOOKUP(C7, products!A:A, products!D:D) -> 7 | J7: =_xlfn.XLOOKUP($I7,categories!$A$1:$A$8,categories!$B$1:$B$8) -> Road Bikes
A8: 672 | B8: 1 | C8: 51 | D8: 2 | E8: 6499.99 | F8: 0.07 | G8: =(E8*B8)-F8 -> 6499.92 | H8: =VLOOKUP($C8,products!$A$1:$F$322,2,FALSE) -> Trek Silque SLR 8 Women's - 2017 | I8: =_xlfn.XLOOKUP(C8, products!A:A, products!D:D) -> 7 | J8: =_xlfn.XLOOKUP($I8,categories!$A$1:$A$8,categories!$B$1:$B$8) -> Road Bikes
A9: 787 | B9: 1 | C9: 51 | D9: 2 | E9: 6499.99 | F9: 0.07 | G9: =(E9*B9)-F9 -> 6499.92 | H9: =VLOOKUP($C9,products!$A$1:$F$322,2,FALSE) -> Trek Silque SLR 8 Women's - 2017 | I9: =_xlfn.XLOOKUP(C9, products!A:A, products!D:D) -> 7 | J9: =_xlfn.XLOOKUP($I9,categories!$A$1:$A$8,categories!$B$1:$B$8) -> Road Bikes
A10: 837 | B10: 1 | C10: 51 | D10: 1 | E10: 6499.99 | F10: 0.05 | G10: =(E10*B10)-F10 -> 6499.94 | H10: =VLOOKUP($C10,products!$A$1:$F$322,2,FALSE) -> Trek Silque SLR 8 Women's - 2017 | I10: =_xlfn.XLOOKUP(C10, products!A:A, products!D:D) -> 7 | J10: =_xlfn.XLOOKUP($I10,categories!$A$1:$A$8,categories!$B$1:$B$8) -> Road Bikes
A11: 904 | B11: 2 | C11: 51 | D11: 2 | E11: 6499.99 | F11: 0.07 | G11: =(E11*B11)-F11 -> 12999.91 | H11: =VLOOKUP($C11,products!$A$1:$F$322,2,FALSE) -> Trek Silque SLR 8 Women's - 2017 | I11: =_xlfn.XLOOKUP(C11, products!A:A, products!D:D) -> 7 | J11: =_xlfn.XLOOKUP($I11,categories!$A$1:$A$8,categories!$B$1:$B$8) -> Road Bikes
A12: 930 | B12: 5 | C12: 51 | D12: 2 | E12: 6499.99 | F12: 0.1 | G12: =(E12*B12)-F12 -> 32499.85 | H12: =VLOOKUP($C12,products!$A$1:$F$322,2,FALSE) -> Trek Silque SLR 8 Women's - 2017 | I12: =_xlfn.XLOOKUP(C12, products!A:A, products!D:D) -> 7 | J12: =_xlfn.XLOOKUP($I12,categories!$A$1:$A$8,categories!$B$1:$B$8) -> Road Bikes
A13: 937 | B13: 2 | C13: 51 | D13: 2 | E13: 6499.99 | F13: 0.07 | G13: =(E13*B13)-F13 -> 12999.91 | H13: =VLOOKUP($C13,products!$A$1:$F$322,2,FALSE) -> Trek Silque SLR 8 Women's - 2017 | I13: =_xlfn.XLOOKUP(C13, products!A:A, products!D:D) -> 7 | J13: =_xlfn.XLOOKUP($I13,categories!$A$1:$A$8,categories!$B$1:$B$8) -> Road Bikes
... A4723: 1573 | B4723: 5 | C4723: 263 | D4723: 2 | E4723: 89.99 | F4723: 0.1 | G4723: =(E4723*B4723)-F4723 -> 449.85 | H4723: =VLOOKUP($C4723,products!$A$1:$F$322,2,FALSE) -> Strider Classic 12 Balance Bike - 2018 | I4723: =_xlfn.XLOOKUP(C4723, products!A:A, products!D:D) -> 1 | J4723: =_xlfn.XLOOKUP($I4723,categories!$A$1:$A$8,categories!$B$1:$B$8) -> Children Bicycles

Sheet staffs
A1: staff_id | B1: first_name | C1: last_name | D1: email | E1: phone | F1: active | G1: store_id | H1: manager_id
A2: 1 | B2: Fabiola | C2: Jackson | D2: fabiola.jackson@bikes.shop | E2: (831) 555-5554 | F2: 1 | G2: 1 | H2: NA
A3: 2 | B3: Mireya | C3: Copeland | D3: mireya.copeland@bikes.shop | E3: (831) 555-5555 | F3: 1 | G3: 1 | H3: 1
A4: 3 | B4: Genna | C4: Serrano | D4: genna.serrano@bikes.shop | E4: (831) 555-5556 | F4: 1 | G4: 1 | H4: 2
A5: 4 | B5: Virgie | C5: Wiggins | D5: virgie.wiggins@bikes.shop | E5: (831) 555-5557 | F5: 1 | G5: 1 | H5: 2
A6: 5 | B6: Jannette | C6: David | D6: jannette.david@bikes.shop | E6: (516) 379-4444 | F6: 1 | G6: 2 | H6: 1
A7: 6 | B7: Marcelene | C7: Boyer | D7: marcelene.boyer@bikes.shop | E7: (516) 379-4445 | F7: 1 | G7: 2 | H7: 5
A8: 7 | B8: Venita | C8: Daniel | D8: venita.daniel@bikes.shop | E8: (516) 379-4446 | F8: 1 | G8: 2 | H8: 5
A9: 8 | B9: Kali | C9: Vargas | D9: kali.vargas@bikes.shop | E9: (972) 530-5555 | F9: 1 | G9: 3 | H9: 1
A10: 9 | B10: Layla | C10: Terrell | D10: layla.terrell@bikes.shop | E10: (972) 530-5556 | F10: 1 | G10: 3 | H10: 7
A11: 10 | B11: Bernardine | C11: Houston | D11: bernardine.houston@bikes.shop | E11: (972) 530-5557 | F11: 1 | G11: 3 | H11: 7

Sheet products
A1: product_id | B1: product_name | C1: brand_id | D1: category_id | E1: model_year | F1: list_price
A2: 1 | B2: Trek 820 - 2016 | C2: 9 | D2: 6 | E2: 2016 | F2: 379.99
A3: 2 | B3: Ritchey Timberwolf Frameset - 2016 | C3: 5 | D3: 6 | E3: 2016 | F3: 749.99
A4: 3 | B4: Surly Wednesday Frameset - 2016 | C4: 8 | D4: 6 | E4: 2016 | F4: 999.99
A5: 4 | B5: Trek Fuel EX 8 29 - 2016 | C5: 9 | D5: 6 | E5: 2016 | F5: 2899.99
A6: 5 | B6: Heller Shagamaw Frame - 2016 | C6: 3 | D6: 6 | E6: 2016 | F6: 1320.99
A7: 6 | B7: Surly Ice Cream Truck Frameset - 2016 | C7: 8 | D7: 6 | E7: 2016 | F7: 469.99
A8: 7 | B8: Trek Slash 8 27.5 - 2016 | C8: 9 | D8: 6 | E8: 2016 | F8: 3999.99
A9: 8 | B9: Trek Remedy 29 Carbon Frameset - 2016 | C9: 9 | D9: 6 | E9: 2016 | F9: 1799.99
A10: 9 | B10: Trek Conduit+ - 2016 | C10: 9 | D10: 5 | E10: 2016 | F10: 2999.99
A11: 10 | B11: Surly Straggler - 2016 | C11: 8 | D11: 4 | E11: 2016 | F11: 1549
A12: 11 | B12: Surly Straggler 650b - 2016 | C12: 8 | D12: 4 | E12: 2016 | F12: 1680.99
A13: 12 | B13: Electra Townie Original 21D - 2016 | C13: 1 | D13: 3 | E13: 2016 | F13: 549.99
... A322: 321 | B322: Trek Checkpoint ALR Frameset - 2019 | C322: 9 | D322: 7 | E322: 2019 | F322: 3199.99

Sheet orders
A1: order_id | B1: customer_id | C1: order_status | D1: order_date | E1: required_date | F1: shipped_date | G1: store_id | H1: staff_id
A2: 1 | B2: 259 | C2: 4 | D2: 42370 | E2: 42372 | F2: 42372 | G2: 1 | H2: 2
A3: 2 | B3: 1212 | C3: 4 | D3: 42370 | E3: 42373 | F3: 42372 | G3: 2 | H3: 6
A4: 3 | B4: 523 | C4: 4 | D4: 42371 | E4: 42374 | F4: 42372 | G4: 2 | H4: 7
A5: 4 | B5: 175 | C5: 4 | D5: 42372 | E5: 42373 | F5: 42374 | G5: 1 | H5: 3
A6: 5 | B6: 1324 | C6: 4 | D6: 42372 | E6: 42375 | F6: 42375 | G6: 2 | H6: 6
A7: 6 | B7: 94 | C7: 4 | D7: 42373 | E7: 42376 | F7: 42374 | G7: 2 | H7: 6
A8: 7 | B8: 324 | C8: 4 | D8: 42373 | E8: 42376 | F8: 42374 | G8: 2 | H8: 6
A9: 8 | B9: 1204 | C9: 4 | D9: 42373 | E9: 42374 | F9: 42374 | G9: 2 | H9: 7
A10: 9 | B10: 60 | C10: 4 | D10: 42374 | E10: 42377 | F10: 42377 | G10: 1 | H10: 2
A11: 10 | B11: 442 | C11: 4 | D11: 42374 | E11: 42375 | F11: 42375 | G11: 2 | H11: 6
A12: 11 | B12: 1326 | C12: 4 | D12: 42374 | E12: 42377 | F12: 42376 | G12: 2 | H12: 7
A13: 12 | B13: 91 | C13: 4 | D13: 42375 | E13: 42377 | F13: 42378 | G13: 1 | H13: 2
... A70: 69 | B70: 1413 | C70: 4 | D70: 42410 | E70: 42412 | F70: 42411 | G70: 2 | H70: 7
A71: 70 | B71: 50 | C71: 3 | D71: 42411 | E71: 42411 | F71: NA | G71: 3 | H71: 9
A72: 71 | B72: 797 | C72: 4 | D72: 42411 | E72: 42414 | F72: 42412 | G72: 2 | H72: 7
A73: 72 | B73: 1386 | C73: 4 | D73: 42412 | E73: 42415 | F73: 42413 | G73: 1 | H73: 2
A74: 73 | B74: 612 | C74: 4 | D74: 42412 | E74: 42415 | F74: 42414 | G74: 2 | H74: 7
A75: 74 | B75: 264 | C75: 4 | D75: 42413 | E75: 42415 | F75: 42415 | G75: 2 | H75: 7
A76: 75 | B76: 587 | C76: 4 | D76: 42414 | E76: 42415 | F76: 42417 | G76: 2 | H76: 6
A77: 76 | B77: 9 | C77: 3 | D77: 42416 | E77: 42416 | F77: NA | G77: 2 | H77: 6
A78: 77 | B78: 385 | C78: 4 | D78: 42416 | E78: 42419 | F78: 42419 | G78: 1 | H78: 2
A79: 78 | B79: 1182 | C79: 4 | D79: 42416 | E79: 42418 | F79: 42419 | G79: 2 | H79: 7
A80: 79 | B80: 529 | C80: 4 | D80: 42417 | E80: 42420 | F80: 42420 | G80: 1 | H80: 3
A81: 80 | B81: 397 | C81: 4 | D81: 42417 | E81: 42420 | F81: 42419 | G81: 2 | H81: 6
A82: 81 | B82: 521 | C82: 4 | D82: 42417 | E82: 42419 | F82: 42418 | G82: 2 | H82: 6
A83: 82 | B83: 1223 | C83: 4 | D83: 42418 | E83: 42421 | F83: 42420 | G83: 2 | H83: 6
A84: 83 | B84: 393 | C84: 4 | D84: 42419 | E84: 42420 | F84: 42420 | G84: 1 | H84: 3
A85: 84 | B85: 317 | C85: 4 | D85: 42420 | E85: 42422 | F85: 42421 | G85: 2 | H85: 7
A86: 85 | B86: 1174 | C86: 4 | D86: 42420 | E86: 42423 | F86: 42421 | G86: 2 | H86: 7
A87: 86 | B87: 276 | C87: 4 | D87: 42421 | E87: 42422 | F87: 42423 | G87: 2 | H87: 7
A88: 87 | B88: 516 | C88: 4 | D88: 42421 | E88: 42422 | F88: 42423 | G88: 2 | H88: 6
A89: 88 | B89: 1069 | C89: 4 | D89: 42421 | E89: 42422 | F89: 42423 | G89: 2 | H89: 6
... A158: 157 | B158: 43 | C158: 4 | D158: 42463 | E158: 42466 | F158: 42466 | G158: 3 | H158: 8
A159: 158 | B159: 117 | C159: 3 | D159: 42464 | E159: 42464 | F159: NA | G159: 3 | H159: 9
A160: 159 | B160: 32 | C160: 4 | D160: 42464 | E160: 42466 | F160: 42466 | G160: 1 | H160: 2
A161: 160 | B161: 205 | C161: 4 | D161: 42464 | E161: 42466 | F161: 42466 | G161: 2 | H161: 7
A162: 161 | B162: 251 | C162: 4 | D162: 42464 | E162: 42467 | F162: 42465 | G162: 2 | H162: 7
A163: 162 | B163: 31 | C163: 4 | D163: 42466 | E163: 42468 | F163: 42467 | G163: 1 | H163: 3
A164: 163 | B164: 1325 | C164: 4 | D164: 42466 | E164: 42467 | F164: 42467 | G164: 2 | H164: 7
A165: 164 | B165: 610 | C165: 4 | D165: 42467 | E165: 42468 | F165: 42469 | G165: 2 | H165: 7
A166: 165 | B166: 574 | C166: 4 | D166: 42468 | E166: 42470 | F166: 42470 | G166: 1 | H166: 3
A167: 166 | B167: 338 | C167: 4 | D167: 42468 | E167: 42471 | F167: 42471 | G167: 2 | H167: 6
A168: 167 | B168: 1034 | C168: 4 | D168: 42468 | E168: 42469 | F168: 42471 | G168: 2 | H168: 7
A169: 168 | B169: 1147 | C169: 4 | D169: 42469 | E169: 42472 | F169: 42471 | G169: 1 | H169: 3
A170: 169 | B170: 99 | C170: 4 | D170: 42470 | E170: 42471 | F170: 42471 | G170: 2 | H170: 7
A171: 170 | B171: 1200 | C171: 4 | D171: 42470 | E171: 42471 | F171: 42473 | G171: 2 | H171: 7
... A185: 184 | B185: 134 | C185: 4 | D185: 42479 | E185: 42481 | F185: 42482 | G185: 2 | H185: 7
A186: 185 | B186: 24 | C186: 3 | D186: 42480 | E186: 42480 | F186: NA | G186: 1 | H186: 2
A187: 186 | B187: 1127 | C187: 4 | D187: 42481 | E187: 42482 | F187: 42484 | G187: 2 | H187: 6
A188: 187 | B188: 183 | C188: 4 | D188: 42482 | E188: 42483 | F188: 42484 | G188: 2 | H188: 6
A189: 188 | B189: 390 | C189: 4 | D189: 42482 | E189: 42483 | F189: 42485 | G189: 2 | H189: 6
A190: 189 | B190: 1288 | C190: 4 | D190: 42483 | E190: 42484 | F190: 42486 | G190: 1 | H190: 2
A191: 190 | B191: 98 | C191: 4 | D191: 42483 | E191: 42485 | F191: 42485 | G191: 2 | H191: 6
A192: 191 | B192: 919 | C192: 4 | D192: 42487 | E192: 42488 | F192: 42488 | G192: 1 | H192: 2
A193: 192 | B193: 728 | C193: 4 | D193: 42487 | E193: 42488 | F193: 42489 | G193: 2 | H193: 7
A194: 193 | B194: 1366 | C194: 4 | D194: 42488 | E194: 42490 | F194: 42490 | G194: 1 | H194: 3
A195: 194 | B195: 558 | C195: 4 | D195: 42488 | E195: 42490 | F195: 42491 | G195: 2 | H195: 7
A196: 195 | B196: 727 | C196: 4 | D196: 42488 | E196: 42491 | F196: 42491 | G196: 2 | H196: 7
A197: 196 | B197: 1247 | C197: 4 | D197: 42488 | E197: 42490 | F197: 42491 | G197: 2 | H197: 6
A198: 197 | B198: 127 | C198: 4 | D198: 42490 | E198: 42493 | F198: 42493 | G198: 2 | H198: 7
... A239: 238 | B239: 1350 | C239: 4 | D239: 42516 | E239: 42519 | F239: 42519 | G239: 2 | H239: 6
A240: 239 | B240: 13 | C240: 3 | D240: 42517 | E240: 42517 | F240: NA | G240: 3 | H240: 9
A241: 240 | B241: 65 | C241: 4 | D241: 42517 | E241: 42519 | F241: 42520 | G241: 2 | H241: 6
A242: 241 | B242: 1082 | C242: 4 | D242: 42517 | E242: 42519 | F242: 42519 | G242: 2 | H242: 7
A243: 242 | B243: 1168 | C243: 4 | D243: 42517 | E243: 42520 | F243: 42520 | G243: 2 | H243: 7
A244: 243 | B244: 802 | C244: 4 | D244: 42517 | E244: 42520 | F244: 42518 | G244: 3 | H244: 8
A245: 244 | B245: 956 | C245: 4 | D245: 42518 | E245: 42519 | F245: 42519 | G245: 2 | H245: 6
A246: 245 | B246: 223 | C246: 4 | D246: 42519 | E246: 42521 | F246: 42520 | G246: 2 | H246: 7
A247: 246 | B247: 17 | C247: 3 | D247: 42520 | E247: 42520 | F247: NA | G247: 2 | H247: 6
A248: 247 | B248: 928 | C248: 4 | D248: 42520 | E248: 42522 | F248: 42522 | G248: 1 | H248: 3
A249: 248 | B249: 1376 | C249: 4 | D249: 42520 | E249: 42522 | F249: 42521 | G249: 2 | H249: 7
A250: 249 | B250: 145 | C250: 4 | D250: 42522 | E250: 42525 | F250: 42525 | G250: 2 | H250: 6
A251: 250 | B251: 150 | C251: 4 | D251: 42522 | E251: 42523 | F251: 42525 | G251: 2 | H251: 7
A252: 251 | B252: 851 | C252: 4 | D252: 42522 | E252: 42525 | F252: 42525 | G252: 2 | H252: 7
A253: 252 | B253: 66 | C253: 4 | D253: 42522 | E253: 42525 | F253: 42523 | G253: 3 | H253: 8
A254: 253 | B254: 1267 | C254: 4 | D254: 42523 | E254: 42526 | F254: 42526 | G254: 2 | H254: 6
A255: 254 | B255: 510 | C255: 4 | D255: 42524 | E255: 42527 | F255: 42526 | G255: 2 | H255: 7
A256: 255 | B256: 801 | C256: 4 | D256: 42524 | E256: 42527 | F256: 42526 | G256: 2 | H256: 7
A257: 256 | B257: 26 | C257: 4 | D257: 42525 | E257: 42526 | F257: 42528 | G257: 2 | H257: 7
A258: 257 | B258: 1314 | C258: 4 | D258: 42526 | E258: 42527 | F258: 42529 | G258: 1 | H258: 3
A259: 258 | B259: 107 | C259: 4 | D259: 42527 | E259: 42528 | F259: 42528 | G259: 2 | H259: 7
... A264: 263 | B264: 1322 | C264: 4 | D264: 42530 | E264: 42531 | F264: 42533 | G264: 2 | H264: 6
A265: 264 | B265: 5 | C265: 3 | D265: 42531 | E265: 42531 | F265: NA | G265: 1 | H265: 3
A266: 265 | B266: 682 | C266: 4 | D266: 42531 | E266: 42533 | F266: 42532 | G266: 2 | H266: 7
A267: 266 | B267: 933 | C267: 4 | D267: 42531 | E267: 42534 | F267: 42534 | G267: 2 | H267: 7
A268: 267 | B268: 282 | C268: 4 | D268: 42532 | E268: 42535 | F268: 42535 | G268: 1 | H268: 3
A269: 268 | B269: 540 | C269: 4 | D269: 42532 | E269: 42535 | F269: 42533 | G269: 1 | H269: 3
A270: 269 | B270: 764 | C270: 4 | D270: 42533 | E270: 42534 | F270: 42536 | G270: 2 | H270: 6
A271: 270 | B271: 879 | C271: 4 | D271: 42533 | E271: 42536 | F271: 42534 | G271: 2 | H271: 7
A272: 271 | B272: 350 | C272: 4 | D272: 42534 | E272: 42537 | F272: 42535 | G272: 2 | H272: 7
A273: 272 | B273: 497 | C273: 4 | D273: 42536 | E273: 42539 | F273: 42537 | G273: 2 | H273: 7
A274: 273 | B274: 1340 | C274: 4 | D274: 42537 | E274: 42540 | F274: 42538 | G274: 2 | H274: 7
A275: 274 | B275: 411 | C275: 4 | D275: 42538 | E275: 42541 | F275: 42539 | G275: 2 | H275: 7
A276: 275 | B276: 1341 | C276: 4 | D276: 42538 | E276: 42540 | F276: 42539 | G276: 2 | H276: 7
A277: 276 | B277: 1227 | C277: 4 | D277: 42539 | E277: 42540 | F277: 42540 | G277: 2 | H277: 6
... A349: 348 | B349: 907 | C349: 4 | D349: 42584 | E349: 42587 | F349: 42586 | G349: 3 | H349: 9
A350: 349 | B350: 30 | C350: 3 | D350: 42585 | E350: 42585 | F350: NA | G350: 1 | H350: 3
A351: 350 | B351: 31 | C351: 3 | D351: 42585 | E351: 42585 | F351: NA | G351: 1 | H351: 3
A352: 351 | B352: 1307 | C352: 4 | D352: 42585 | E352: 42588 | F352: 42586 | G352: 1 | H352: 2
...

Sheet order_items
A1: order_id | B1: item_id | C1: product_id | D1: quantity | E1: list_price | F1: discount | G1: total_price | H1: product name | I1: category_id | J1: category_name
A2: 1 | B2: 1 | C2: 20 | D2: 1 | E2: 599.99 | F2: 0.2 | G2: 599.79 | H2: Electra Townie Original 7D EQ - Women's - 2016 | I2: =_xlfn.XLOOKUP(C2, products!A:A, products!D:D) -> 3 | J2: Cruisers Bicycles
A3: 1 | B3: 2 | C3: 8 | D3: 2 | E3: 1799.99 | F3: 0.07 | G3: 3599.91 | H3: Trek Remedy 29 Carbon Frameset - 2016 | I3: =_xlfn.XLOOKUP(C3, products!A:A, products!D:D) -> 6 | J3: Mountain Bikes
A4: 1 | B4: 3 | C4: 10 | D4: 2 | E4: 1549 | F4: 0.05 | G4: 4646.95 | H4: Surly Straggler - 2016 | I4: =_xlfn.XLOOKUP(C4, products!A:A, products!D:D) -> 4 | J4: Cyclocross Bicycles
A5: 1 | B5: 4 | C5: 16 | D5: 2 | E5: 599.99 | F5: 0.05 | G5: 2399.91 | H5: Electra Townie Original 7D EQ - 2016 | I5: =_xlfn.XLOOKUP(C5, products!A:A, products!D:D) -> 3 | J5: Cruisers Bicycles
A6: 1 | B6: 5 | C6: 4 | D6: 1 | E6: 2899.99 | F6: 0.2 | G6: 14499.75 | H6: Trek Fuel EX 8 29 - 2016 | I6: =_xlfn.XLOOKUP(C6, products!A:A, products!D:D) -> 6 | J6: Mountain Bikes
A7: 2 | B7: 1 | C7: 20 | D7: 1 | E7: 599.99 | F7: 0.07 | G7: 599.92 | H7: Electra Townie Original 7D EQ - Women's - 2016 | I7: =_xlfn.XLOOKUP(C7, products!A:A, products!D:D) -> 3 | J7: Cruisers Bicycles
A8: 2 | B8: 2 | C8: 16 | D8: 2 | E8: 599.99 | F8: 0.05 | G8: 1199.93 | H8: Electra Townie Original 7D EQ - 2016 | I8: =_xlfn.XLOOKUP(C8, products!A:A, products!D:D) -> 3 | J8: Cruisers Bicycles
A9: 3 | B9: 1 | C9: 3 | D9: 1 | E9: 999.99 | F9: 0.05 | G9: 999.94 | H9: Surly Wednesday Frameset - 2016 | I9: =_xlfn.XLOOKUP(C9, products!A:A, products!D:D) -> 6 | J9: Mountain Bikes
A10: 3 | B10: 2 | C10: 20 | D10: 1 | E10: 599.99 | F10: 0.05 | G10: 1199.93 | H10: Electra Townie Original 7D EQ - Women's - 2016 | I10: =_xlfn.XLOOKUP(C10, products!A:A, products!D:D) -> 3 | J10: Cruisers Bicycles
A11: 4 | B11: 1 | C11: 2 | D11: 2 | E11: 749.99 | F11: 0.1 | G11: 749.89 | H11: Ritchey Timberwolf Frameset - 2016 | I11: =_xlfn.XLOOKUP(C11, products!A:A, products!D:D) -> 6 | J11: Mountain Bikes
A12: 5 | B12: 1 | C12: 10 | D12: 2 | E12: 1549 | F12: 0.05 | G12: 1548.95 | H12: Surly Straggler - 2016 | I12: =_xlfn.XLOOKUP(C12, products!A:A, products!D:D) -> 4 | J12: Cyclocross Bicycles
A13: 5 | B13: 2 | C13: 17 | D13: 1 | E13: 429 | F13: 0.07 | G13: 857.93 | H13: Pure Cycles Vine 8-Speed - 2016 | I13: =_xlfn.XLOOKUP(C13, products!A:A, products!D:D) -> 3 | J13: Cruisers Bicycles
... A4723: 1615 | B4723: 3 | C4723: 182 | D4723: 1 | E4723: 2499.99 | F4723: 0.2 | G4723: 7499.77 | H4723: Trek Domane SL 5 Disc - 2018 | I4723: =_xlfn.XLOOKUP(C4723, products!A:A, products!D:D) -> 7 | J4723: Road Bikes

Sheet customers
A1: customer_id | B1: first_name | C1: last_name | D1: phone | E1: email | F1: street | G1: city | H1: state | I1: zip_code
A2: 1 | B2: Debra | C2: Burks | D2: NA | E2: debra.burks@yahoo.com | F2: 9273 Thorne Ave. | G2: Orchard Park | H2: NY | I2: 14127
A3: 2 | B3: Kasha | C3: Todd | D3: NA | E3: kasha.todd@yahoo.com | F3: 910 Vine Street | G3: Campbell | H3: CA | I3: 95008
A4: 3 | B4: Tameka | C4: Fisher | D4: NA | E4: tameka.fisher@aol.com | F4: 769C Honey Creek St. | G4: Redondo Beach | H4: CA | I4: 90278
A5: 4 | B5: Daryl | C5: Spence | D5: NA | E5: daryl.spence@aol.com | F5: 988 Pearl Lane | G5: Uniondale | H5: NY | I5: 11553
A6: 5 | B6: Charolette | C6: Rice | D6: (916) 381-6003 | E6: charolette.rice@msn.com | F6: 107 River Dr. | G6: Sacramento | H6: CA | I6: 95820
A7: 6 | B7: Lyndsey | C7: Bean | D7: NA | E7: lyndsey.bean@hotmail.com | F7: 769 West Road | G7: Fairport | H7: NY | I7: 14450
A8: 7 | B8: Latasha | C8: Hays | D8: (716) 986-3359 | E8: latasha.hays@hotmail.com | F8: 7014 Manor Station Rd. | G8: Buffalo | H8: NY | I8: 14215
A9: 8 | B9: Jacquline | C9: Duncan | D9: NA | E9: jacquline.duncan@yahoo.com | F9: 15 Brown St. | G9: Jackson Heights | H9: NY | I9: 11372
A10: 9 | B10: Genoveva | C10: Baldwin | D10: NA | E10: genoveva.baldwin@msn.com | F10: 8550 Spruce Drive | G10: Port Washington | H10: NY | I10: 11050
A11: 10 | B11: Pamelia | C11: Newman | D11: NA | E11: pamelia.newman@gmail.com | F11: 476 Chestnut Ave. | G11: Monroe | H11: NY | I11: 10950
A12: 11 | B12: Deshawn | C12: Mendoza | D12: NA | E12: deshawn.mendoza@yahoo.com | F12: 8790 Cobblestone Street | G12: Monsey | H12: NY | I12: 10952
A13: 12 | B13: Robby | C13: Sykes | D13: (516) 583-7761 | E13: robby.sykes@hotmail.com | F13: 486 Rock Maple Street | G13: Hempstead | H13: NY | I13: 11550
... A1446: 1445 | B1446: Ester | C1446: Acevedo | D1446: NA | E1446: ester.acevedo@gmail.com | F1446: 671 Miles Court | G1446: San Lorenzo | H1446: CA | I1446: 94580

Sheet categories
A1: category_id | B1: category_name
A2: 1 | B2: Children Bicycles
A3: 2 | B3: Comfort Bicycles
A4: 3 | B4: Cruisers Bicycles
A5: 4 | B5: Cyclocross Bicycles
A6: 5 | B6: Electric Bikes
A7: 6 | B7: Mountain Bikes
A8: 7 | B8: Road Bikes

Sheet brands
A1: brand_id | B1: brand_name
A2: 1 | B2: Electra
A3: 2 | B3: Haro
A4: 3 | B4: Heller
A5: 4 | B5: Pure Cycles
A6: 5 | B6: Ritchey
A7: 6 | B7: Strider
A8: 7 | B8: Sun Bicycles
A9: 8 | B9: Surly
A10: 9 | B10: Trek

Sheet pivot table
A3: Row Labels | B3: Sum of total_sales
A4: Children Bicycles | B4: 492837.79
A5: Comfort Bicycles | B5: 640954.19
A6: Cruisers Bicycles | B6: 1707469.6
A7: Cyclocross Bicycles | B7: 1194483
A8: Electric Bikes | B8: 1554872.9
A9: Mountain Bikes | B9: 4646413.7
A10: Road Bikes | B10: 2796129.4
A11: Grand Total | B11: 13033161
